solavis/__init__.py
solavis/contrib/__init__.py
solavis/contrib/middleware.py
solavis/contrib/request.py
solavis/core/__init__.py
solavis/core/container.py
solavis/core/middleware.py
solavis/core/pipeline.py
solavis/core/request.py
solavis/core/response.py
solavis/core/spider.py
solavis/util/__init__.py
solavis/util/async_helper.py
solavis-0.1a1.dev2.dist-info/LICENSE
solavis-0.1a1.dev2.dist-info/METADATA
solavis-0.1a1.dev2.dist-info/WHEEL
solavis-0.1a1.dev2.dist-info/top_level.txt
solavis-0.1a1.dev2.dist-info/RECORD
