Metadata-Version: 2.1
Name: solavis
Version: 0.1a1.dev2
Summary: lightweight async crawler framework
Home-page: https://github.com/jstzwj/solavis.git
Author: JunWang
Author-email: jstzwj@aliyun.com
License: MIT
Keywords: crawler
Platform: UNKNOWN
Requires-Python: >=3.7
Requires-Dist: lxml (==4.3.3)
Requires-Dist: requests (==2.21.0)
Requires-Dist: aiohttp (==3.6.2)
Requires-Dist: aiosqlite (==0.10.0)
